<elements>
	<info>
		<name>Barbarian Revisited</name>
		<description>Content created by the Chisato Bailey</description>
		<author url="https://github.com/Chisatobailey/RPG-Stuff">Chisato Bailey</author>
		<update version="1.4.0">
			<file name="Barbarian Revisited.xml" url="https://raw.githubusercontent.com/Chisatobailey/RPG-Stuff/Ian's-Additions/Barbarian%20Revisited.xml" />
		</update>
	</info>
    <element name="Rampaging Charge" type="Class Feature" source="Ian's Additions" id="ID_IANSADDITIONS_BARBARIANREVISITED_CLASS_FEATURE_BARBARIAN_RAMPAGING_CHARGE">
		<description>
			<p>Beginning at level three, while raging a barbarian may use their attack action to charge through the enemy’s line knocking their opponents aside or even smashing them to the ground.</p>
			<p class="indent">While Raging; move up to 30 feet through enemy spaces. Each enemy takes 1d4 bludgeoning damage and must make a dexterity saving throw at DC {{barbarian:shove}} to keep from being either shoved one square or knocked prone (your choice). This action does not provoke opportunity attacks.</p>
		</description>
		<sheet action="Attack Action">
			<description>While Raging; move up to 30 feet through enemy spaces. Each enemy takes 1d4 bludgeoning damage and must make a dexterity saving throw at DC {{barbarian:shove}} to keep from being either shoved one square or knocked prone (your choice). This action does not provoke opportunity attacks.</description>
		</sheet>
		<rules>
			<stat name="barbarian:shove" value="8" />
			<stat name="barbarian:shove" value="proficiency" />
			<stat name="barbarian:shove" value="strength:modifier" />
		</rules>
	</element>
    <element name="Vicious Taunt" type="Class Feature" source="Ian's Additions" id="ID_IANSADDITIONS_BARBARIANREVISITED_CLASS_FEATURE_BARBARIAN_VICIOUS_TAUNT">
		<description>
			<p>Barbarians excel at maddening enemies until they make a mistake. You may Taunt up to 4 enemies. They must make a Wisdom saving throw at DC {{barbarian:taunt}} to resist mark. Marked foes must attack only you until succeeding on a save (minimum 1 turn).</p>
	        <p class="indent">In addition, one enemy within 15 feet will immediately charge the barbarian and make an attack at disadvantage. If this attack fails, the enemy is dazed for one turn.</p>
		</description>
		<sheet action="Bonus Action">
			<description>-	You may Taunt up to 4 enemies. They must make a Wisdom saving throw at DC {{barbarian:taunt}} to resist mark. Marked foes must attack only you until succeeding on a save (minimum 1 turn). You may choose one enemy within 15 feet of you to charge you. The opponent must make a melee attack at disadvantage. If the attack misses they are dazed for 1 turn. </description>
		</sheet>
		<rules>
			<stat name="barbarian:taunt" value="8" />
			<stat name="barbarian:taunt" value="proficiency" />
			<stat name="barbarian:taunt" value="strength:modifier" />
		</rules>
	</element>
    <element name="Charging Blow" type="Class Feature" source="Ian's Additions" id="ID_IANSADDITIONS_BARBARIANREVISITED_CLASS_FEATURE_BARBARIAN_CHARGING_BLOW">
		<description>
			<p>Beginning at level 5, barbarians may charge their enemy before making an attack. Striking an opponent after this charge, pushes them back and possibly knocks them to the ground. </p>
			<p class="indent">Move at least 10 feet and make a melee attack. If the attack hits, the target is shoved one space and must make either a strength or a dexterity (target's choice) saving throw at DC {{barbarian:shove}} to keep from being knocked prone.</p>
		</description>
		<sheet>
			<description>Move at least 10 feet and make a melee attack. If the attack hits, the target is shoved one space and must make a dexterity saving throw at DC {{barbarian:shove}} to keep from being knocked prone.</description>
		</sheet>
	</element>
    <element name="Feral Assault" type="Class Feature" source="Ian's Additions" id="ID_IANSADDITIONS_BARBARIANREVISITED_CLASS_FEATURE_BARBARIAN_FERAL_ASSAULT">
		<description>
			<p>Beginning at 7th level, a barbarian may choose to make a powerful sweeping attack in place of a normal attack striking multiple opponents at once.</p>
			<p class="indent"></p>
			<p class="indent"></p>
		</description>
		<sheet action="Attack Action">
			<description usage="{{strength:modifier:half}}/Long Rest">Make a single attack that strikes up to 3 opponents adjacent to you. If the attack roll hits an enemy’s AC that enemy takes weapon damage only (do not add ability modifier).</description>
		</sheet>
	</element>

    <append id="ID_WOTC_PHB_CLASS_BARBARIAN">
  		<rules>
    		<grant type="Class Feature" id="ID_IANSADDITIONS_BARBARIANREVISITED_CLASS_FEATURE_BARBARIAN_RAMPAGING_CHARGE" level="3" />
    		<grant type="Class Feature" id="ID_IANSADDITIONS_BARBARIANREVISITED_CLASS_FEATURE_BARBARIAN_VICIOUS_TAUNT" level="5" />
    		<grant type="Class Feature" id="ID_IANSADDITIONS_BARBARIANREVISITED_CLASS_FEATURE_BARBARIAN_CHARGING_BLOW" level="5" />
    		<grant type="Class Feature" id="ID_IANSADDITIONS_BARBARIANREVISITED_CLASS_FEATURE_BARBARIAN_FERAL_ASSAULT" level="7" />
  		</rules>
	</append>
</elements>